tmg_etl_pipeline/__init__.py
tmg_etl_pipeline/conf.py
tmg_etl_pipeline/etl.py
tmg_etl_pipeline/logs.py
tmg_etl_pipeline-0.0.9.dist-info/licenses/LICENSE
tmg_etl_pipeline-0.0.9.dist-info/METADATA
tmg_etl_pipeline-0.0.9.dist-info/WHEEL
tmg_etl_pipeline-0.0.9.dist-info/top_level.txt
tmg_etl_pipeline-0.0.9.dist-info/RECORD
