Metadata-Version: 2.4
Name: tmg-etl-pipeline
Version: 0.0.9
Summary: TMG ETL pipeline
Home-page: https://github.com/telegraph/tmg-etl-pipeline
Author: TMG Data Platform team
Author-email: data.platform@telegraph.co.uk
License: Apache 2.0
Classifier: Intended Audience :: Developers
Classifier: License :: OSI Approved :: Apache Software License
Classifier: Programming Language :: Python
Classifier: Programming Language :: Python :: 3
Classifier: Operating System :: OS Independent
Requires-Python: >=3.6
License-File: LICENSE
Requires-Dist: google-cloud-secret-manager==2.23.2
Requires-Dist: PyYAML==6.0.2
Dynamic: author
Dynamic: author-email
Dynamic: classifier
Dynamic: description
Dynamic: home-page
Dynamic: license
Dynamic: license-file
Dynamic: requires-dist
Dynamic: requires-python
Dynamic: summary
